coffee/__init__.py
coffee/agent.py
coffee/api_client.py
coffee/config.py
coffee/log.py
coffee/models.py
coffee/session.py
coffee/task.py
coffee/types/__init__.py
coffee/types/agent.py
coffee/types/model.py
coffee/types/tool.py
coffee/types/user.py
coffee_agent_kit-0.1.0.dist-info/METADATA
coffee_agent_kit-0.1.0.dist-info/WHEEL
coffee_agent_kit-0.1.0.dist-info/top_level.txt
coffee_agent_kit-0.1.0.dist-info/RECORD
