Metadata-Version: 2.2
Name: coffee-agent-kit
Version: 0.1.0
Summary: Add your description here
Author-email: "Coffee.fun" <info@coffee.fun>
License: MIT
Project-URL: Homepage, https://pypi.org/project/coffee-agent-kit/0.1.0/
Project-URL: Repository, https://pypi.org/project/coffee-agent-kit/0.1.0/
Requires-Python: >=3.13
Requires-Dist: passlib>=1.7.4
Requires-Dist: pydantic>=2.10.6
Requires-Dist: requests>=2.32.3
Requires-Dist: rich>=13.9.4
